{"arch_packages":"arm_cortex-a15_neon-vfpv4","default_packages":["base-files","busybox","ca-bundle","dnsmasq","dropbear","firewall","fstools","ip6tables","iptables","kmod-ata-ahci","kmod-ata-ahci-platform","kmod-ath10k-ct","kmod-gpio-button-hotplug","kmod-ipt-offload","kmod-leds-gpio","kmod-phy-qcom-ipq806x-usb","kmod-usb-dwc3-qcom","kmod-usb-ledtrig-usbport","kmod-usb-ohci","kmod-usb2","kmod-usb3","libc","libgcc","libustream-wolfssl","logd","mtd","netifd","odhcp6c","odhcpd-ipv6only","opkg","ppp","ppp-mod-pppoe","procd","swconfig","uboot-envtools","uci","uclient-fetch","urandom-seed","urngd","wpad-basic-wolfssl"],"metadata_version":1,"profiles":{"netgear_r7800":{"device_packages":["ath10k-firmware-qca9984-ct"],"image_prefix":"openwrt-21.02.0-rc3-ipq806x-generic-netgear_r7800","images":[{"filesystem":"squashfs","name":"openwrt-21.02.0-rc3-ipq806x-generic-netgear_r7800-squashfs-factory.img","sha256":"50e9c1a364eb4e09a4aa047bc67914515ad9b376d92bd2e939d59fdea90eb57d","type":"factory"},{"filesystem":"squashfs","name":"openwrt-21.02.0-rc3-ipq806x-generic-netgear_r7800-squashfs-sysupgrade.bin","sha256":"75218626dad4ee720fe50203fdd05395c60f5dfc7c3293c3006f90f9fbdaab3d","type":"sysupgrade"}],"supported_devices":["netgear,r7800","r7800"],"titles":[{"model":"Nighthawk X4S R7800","vendor":"NETGEAR"}]}},"source_date_epoch":"1623621739","target":"ipq806x/generic","version_code":"r16172-2aba3e9784","version_number":"21.02.0-rc3"}